MANIFEST.in
README.rst
setup.py
version
src/falcon_cors/__init__.py
src/falcon_cors/log.py
src/falcon_cors/middleware.py
src/falcon_cors.egg-info/PKG-INFO
src/falcon_cors.egg-info/SOURCES.txt
src/falcon_cors.egg-info/dependency_links.txt
src/falcon_cors.egg-info/requires.txt
src/falcon_cors.egg-info/top_level.txt